__init__.py
ragbuilder/__init__.py
ragbuilder/_version.py
ragbuilder/analytics.py
ragbuilder/custom_components.py
ragbuilder/data_processor.py
ragbuilder/eval.py
ragbuilder/evaldb_dmls.py
ragbuilder/executor.py
ragbuilder/generate_data.py
ragbuilder/ragbuilder.py
ragbuilder/sampler.py
ragbuilder/config/__init__.py
ragbuilder/config/base.py
ragbuilder/config/components.py
ragbuilder/config/data_ingest.py
ragbuilder/config/generation.py
ragbuilder/config/retriever.py
ragbuilder/core/__init__.py
ragbuilder/core/builder.py
ragbuilder/core/callbacks.py
ragbuilder/core/config_store.py
ragbuilder/core/document_store.py
ragbuilder/core/exceptions.py
ragbuilder/core/logging_utils.py
ragbuilder/core/results.py
ragbuilder/core/telemetry.py
ragbuilder/core/utils.py
ragbuilder/data_ingest/__init__.py
ragbuilder/data_ingest/evaluation.py
ragbuilder/data_ingest/optimization.py
ragbuilder/data_ingest/pipeline.py
ragbuilder/generation/__init__.py
ragbuilder/generation/config.yaml
ragbuilder/generation/evaluation.py
ragbuilder/generation/optimization.py
ragbuilder/generation/pipeline.py
ragbuilder/generation/prompt_templates.py
ragbuilder/generation/prompts.yaml
ragbuilder/generation/rewrite_question.py
ragbuilder/generation/sample_retriever.py
ragbuilder/graph_utils/__init__.py
ragbuilder/graph_utils/graph_loader.py
ragbuilder/graph_utils/graph_retriever.py
ragbuilder/langchain_module/__init__.py
ragbuilder/langchain_module/_version.py
ragbuilder/langchain_module/common.py
ragbuilder/langchain_module/config.yml
ragbuilder/langchain_module/chunkingstrategy/__init__.py
ragbuilder/langchain_module/chunkingstrategy/langchain_chunking.py
ragbuilder/langchain_module/embedding_model/__init__.py
ragbuilder/langchain_module/embedding_model/embedding.py
ragbuilder/langchain_module/llms/__init__.py
ragbuilder/langchain_module/llms/llmConfig.py
ragbuilder/langchain_module/loader/__init__.py
ragbuilder/langchain_module/loader/loader.py
ragbuilder/langchain_module/rag/__init__.py
ragbuilder-0.1.6.dist-info/licenses/LICENSE
ragbuilder-0.1.6.dist-info/METADATA
ragbuilder-0.1.6.dist-info/WHEEL
ragbuilder-0.1.6.dist-info/entry_points.txt
ragbuilder-0.1.6.dist-info/top_level.txt
ragbuilder-0.1.6.dist-info/RECORD
