Metadata-Version: 2.4
Name: ragbuilder
Version: 0.1.6
Summary: RagBuilder SDK - Create optimal Production-ready RAG pipelines
Author-email: Ashwin Aravind <ashwin@krux.ai>, Aravind Parameswaran <aravind@krux.ai>
License: Apache-2.0
Requires-Python: >=3.7
License-File: LICENSE
Requires-Dist: chromadb
Requires-Dist: datasets>=2.18.0
Requires-Dist: fastapi>=0.100.0
Requires-Dist: jinja2
Requires-Dist: langchain>=0.3.24
Requires-Dist: langchain_chroma==0.2.3
Requires-Dist: langchain-community==0.3.22
Requires-Dist: langchain-core==0.3.55
Requires-Dist: langchain-huggingface==0.1.2
Requires-Dist: langchain-openai==0.3.14
Requires-Dist: opentelemetry-api>=1.23.0
Requires-Dist: opentelemetry-sdk>=1.23.0
Requires-Dist: opentelemetry-exporter-otlp>=1.23.0
Requires-Dist: optuna
Requires-Dist: platformdirs
Requires-Dist: pydantic>=2.0.0
Requires-Dist: python-dotenv
Requires-Dist: ragas==0.2.14
Requires-Dist: rerankers
Requires-Dist: rich>=13.0.0
Requires-Dist: sentence-transformers
Requires-Dist: tenacity==8.4.2
Requires-Dist: rank-bm25
Requires-Dist: uvicorn>=0.30.0
Provides-Extra: graph
Requires-Dist: neo4j>=5.23.0; extra == "graph"
Requires-Dist: langchain-community[neo4j]; extra == "graph"
Provides-Extra: vectorstores
Requires-Dist: elasticsearch>=8.0.0; extra == "vectorstores"
Requires-Dist: faiss-cpu>=1.7.4; extra == "vectorstores"
Requires-Dist: pinecone-client>=3.0.0; extra == "vectorstores"
Requires-Dist: pymilvus>=2.3.0; extra == "vectorstores"
Requires-Dist: qdrant-client>=1.7.0; extra == "vectorstores"
Requires-Dist: weaviate-client>=3.25.0; extra == "vectorstores"
Requires-Dist: langchain-pinecone; extra == "vectorstores"
Requires-Dist: langchain-weaviate; extra == "vectorstores"
Requires-Dist: langchain-qdrant; extra == "vectorstores"
Requires-Dist: langchain-milvus; extra == "vectorstores"
Requires-Dist: langchain-postgres; extra == "vectorstores"
Requires-Dist: langchain-elasticsearch; extra == "vectorstores"
Provides-Extra: document-processors
Requires-Dist: pymupdf>=1.23.0; extra == "document-processors"
Requires-Dist: python-docx>=1.0.0; extra == "document-processors"
Requires-Dist: pikepdf>=8.11.0; extra == "document-processors"
Requires-Dist: pandoc>=2.3; extra == "document-processors"
Requires-Dist: pypdf>=3.17.0; extra == "document-processors"
Requires-Dist: markdown>=3.5.0; extra == "document-processors"
Requires-Dist: beautifulsoup4>=4.12.0; extra == "document-processors"
Requires-Dist: unstructured[all-docs]>=0.11.0; extra == "document-processors"
Provides-Extra: all
Requires-Dist: ragbuilder[graph]; extra == "all"
Requires-Dist: ragbuilder[vectorstores]; extra == "all"
Requires-Dist: ragbuilder[document_processors]; extra == "all"
Dynamic: license-file
